java_based_implementation/__init__.py
java_based_implementation/api_impl.py
java_based_implementation/gateway_server.py
java_based_implementation/java_gateway.py
java_based_implementation/util/__init__.py
java_based_implementation/util/constants.py
java_based_implementation/util/exceptions.py
java_based_implementation/util/java_utils.py
paimon_python_api/__init__.py
paimon_python_api/catalog.py
paimon_python_api/commit_message.py
paimon_python_api/read_builder.py
paimon_python_api/split.py
paimon_python_api/table.py
paimon_python_api/table_commit.py
paimon_python_api/table_read.py
paimon_python_api/table_scan.py
paimon_python_api/table_write.py
paimon_python_api/write_builder.py
paimon_python-0.9.0.dev1.dist-info/LICENSE
paimon_python-0.9.0.dev1.dist-info/METADATA
paimon_python-0.9.0.dev1.dist-info/NOTICE
paimon_python-0.9.0.dev1.dist-info/WHEEL
paimon_python-0.9.0.dev1.dist-info/top_level.txt
paimon_python-0.9.0.dev1.dist-info/RECORD
